redisai/__init__.py
redisai/client.py
redisai/command_builder.py
redisai/dag.py
redisai/pipeline.py
redisai/postprocessor.py
redisai/utils.py
redisai-1.3.0.dist-info/METADATA
redisai-1.3.0.dist-info/WHEEL
redisai-1.3.0.dist-info/LICENSE
redisai-1.3.0.dist-info/RECORD
