Metadata-Version: 2.1
Name: redisai
Version: 1.3.0
Summary: RedisAI Python Client
License: BSD-3-Clause
Author: Redis
Author-email: oss@redis.com
Requires-Python: >=3.8,<=4.0.0
Classifier: Development Status :: 5 - Production/Stable
Classifier: Intended Audience :: Developers
Classifier: License :: OSI Approved :: BSD License
Classifier: Programming Language :: Python
Classifier: Programming Language :: Python :: 3
Classifier: Programming Language :: Python :: 3.8
Classifier: Programming Language :: Python :: 3.9
Classifier: Programming Language :: Python :: 3.10
Classifier: Programming Language :: Python :: 3.11
Classifier: Programming Language :: Python :: 3.10
Classifier: Programming Language :: Python :: 3.11
Classifier: Programming Language :: Python :: 3.8
Classifier: Programming Language :: Python :: 3.9
Classifier: Topic :: Database
Requires-Dist: Deprecated (>=1.2.12,<2.0.0)
Requires-Dist: hiredis (>=0.20)
Requires-Dist: numpy (>=1.19.5)
Requires-Dist: pytest (>=7.2.1,<8.0.0)
Requires-Dist: redis (>=4.1.4,<5.0.0)
Requires-Dist: six (>=1.10.0)
Project-URL: Documentation, https://redisai.readhtedocs.io
Project-URL: Homepage, https://oss..com/redisai/
Project-URL: Project URL, https://redisai.io
Project-URL: Repository, https://github.com/RedisAI/redisai-py
Project-URL: Tracker, https://github.com/RedisAI/redisai-py/issues
